{
  "name": "sellos",
  "base": "PersistedModel",
  "idInjection": true,
  "options": {
    "validateUpsert": true
  },
  "properties": {
    "id": {
      "type": "number",
      "required": true
    },
    "consecutivoIni": {
      "type": "number"
    },
    "consecutivoFin": {
      "type": "number"
    },
    "ruta": {
      "type": "string"
    },
    "fecha": {
      "type": "date"
    },
    "tipo": {
      "type": "string"
    },
    "responsable": {
      "type": "string"
    }
  },
  "validations": [],
  "relations": {},
  "acls": [],
  "methods": {}
}
